<?xml version="1.0" encoding="utf-8"?>
<!-- Created by ModBuddy on 2023-12-08 오후 9:10:18 -->
<GameData>
	<Buildings>
		<Update>
			<Where Type="BUILDING_WINDMILL" />
			<Set Flat="0" />
		</Update>
	</Buildings>
	<Language_ko_KR>
		<Update>
			<Where Tag="TXT_KEY_BUILDING_WINDMILL_HELP"/>
			<Set Text="건물을 건설할 때 [ICON_PRODUCTION]생산 보너스를 [COLOR_POSITIVE_TEXT]10%[ENDCOLOR] 제공합니다."/>
		</Update>
		<Update>
			<Where Tag="TXT_KEY_BUILDING_WINDMILL_STRATEGY"/>
			<Set Text="풍차는 도시의 생산을 증가시키는 르네상스시대 건물입니다."/>
		</Update>
		<Update>
			<Where Tag="TXT_KEY_TECH_ECONOMICS_HELP"/>
			<Set Text="[ICON_PRODUCTION]생산을 증가시키는 [COLOR_POSITIVE_TEXT]풍차[ENDCOLOR]를 만들 수 있습니다."/>
		</Update>
	</Language_ko_KR>
</GameData>